PyElevate/__init__.py
PyElevate/posix.py
PyElevate/windows.py
pyelevate-0.1.2.dist-info/licenses/LICENSE
pyelevate-0.1.2.dist-info/METADATA
pyelevate-0.1.2.dist-info/WHEEL
pyelevate-0.1.2.dist-info/entry_points.txt
pyelevate-0.1.2.dist-info/top_level.txt
pyelevate-0.1.2.dist-info/RECORD
